itkwasm_dicom_wasi/__init__.py
itkwasm_dicom_wasi/_version.py
itkwasm_dicom_wasi/apply_presentation_state_to_image.py
itkwasm_dicom_wasi/read_dicom_encapsulated_pdf.py
itkwasm_dicom_wasi/read_image_dicom_file_series.py
itkwasm_dicom_wasi/read_overlapping_segmentation.py
itkwasm_dicom_wasi/read_segmentation.py
itkwasm_dicom_wasi/structured_report_to_html.py
itkwasm_dicom_wasi/structured_report_to_text.py
itkwasm_dicom_wasi/write_multi_segmentation.py
itkwasm_dicom_wasi/write_overlapping_segmentation.py
itkwasm_dicom_wasi/write_rt_struct.py
itkwasm_dicom_wasi/write_segmentation.py
itkwasm_dicom_wasi/wasm_modules/apply-presentation-state-to-image.wasi.wasm
itkwasm_dicom_wasi/wasm_modules/read-dicom-encapsulated-pdf.wasi.wasm
itkwasm_dicom_wasi/wasm_modules/read-image-dicom-file-series.wasi.wasm
itkwasm_dicom_wasi/wasm_modules/read-overlapping-segmentation.wasi.wasm
itkwasm_dicom_wasi/wasm_modules/read-segmentation.wasi.wasm
itkwasm_dicom_wasi/wasm_modules/structured-report-to-html.wasi.wasm
itkwasm_dicom_wasi/wasm_modules/structured-report-to-text.wasi.wasm
itkwasm_dicom_wasi/wasm_modules/write-multi-segmentation.wasi.wasm
itkwasm_dicom_wasi/wasm_modules/write-overlapping-segmentation.wasi.wasm
itkwasm_dicom_wasi/wasm_modules/write-rt-struct.wasi.wasm
itkwasm_dicom_wasi/wasm_modules/write-segmentation.wasi.wasm
itkwasm_dicom_wasi-7.6.4.dist-info/METADATA
itkwasm_dicom_wasi-7.6.4.dist-info/WHEEL
itkwasm_dicom_wasi-7.6.4.dist-info/RECORD
