Metadata-Version: 2.3
Name: itkwasm-dicom-wasi
Version: 7.6.4
Dynamic: Summary
Project-URL: Home, https://itk-wasm-dicom-python-docs.on.fleek.co
Project-URL: Source, https://github.com/InsightSoftwareConsortium/ITK-Wasm
Project-URL: Issues, https://github.com/InsightSoftwareConsortium/ITK-Wasm/issues
Keywords: itkwasm,wasi,webassembly
Classifier: Development Status :: 4 - Beta
Classifier: Environment :: WebAssembly
Classifier: Environment :: WebAssembly :: Emscripten
Classifier: Environment :: WebAssembly :: WASI
Classifier: Intended Audience :: Developers
Classifier: Intended Audience :: Science/Research
Classifier: License :: OSI Approved :: Apache Software License
Classifier: Programming Language :: C++
Classifier: Programming Language :: Python
Classifier: Programming Language :: Python :: 3
Classifier: Programming Language :: Python :: 3.8
Classifier: Programming Language :: Python :: 3.9
Classifier: Programming Language :: Python :: 3.10
Classifier: Programming Language :: Python :: 3.11
Requires-Python: >=3.8
Requires-Dist: importlib-resources
Requires-Dist: itkwasm-compare-images
Requires-Dist: itkwasm-image-io
Requires-Dist: itkwasm>=1.0.b131
